hug/__init__.py
hug/__main__.py
hug/_empty.py
hug/_version.py
hug/api.py
hug/authentication.py
hug/decorators.py
hug/defaults.py
hug/development_runner.py
hug/directives.py
hug/exceptions.py
hug/format.py
hug/input_format.py
hug/interface.py
hug/introspect.py
hug/json_module.py
hug/middleware.py
hug/output_format.py
hug/redirect.py
hug/route.py
hug/routing.py
hug/store.py
hug/test.py
hug/this.py
hug/transform.py
hug/types.py
hug/use.py
hug/validate.py
hug-2.5.6.dist-info/LICENSE
hug-2.5.6.dist-info/METADATA
hug-2.5.6.dist-info/WHEEL
hug-2.5.6.dist-info/entry_points.txt
hug-2.5.6.dist-info/top_level.txt
hug-2.5.6.dist-info/RECORD
